easyblocks/__init__.py
easyblocks/easyblocks.py
easyblocks/utils.py
easyblocks-0.0.0.26a0.dist-info/LICENSE
easyblocks-0.0.0.26a0.dist-info/METADATA
easyblocks-0.0.0.26a0.dist-info/WHEEL
easyblocks-0.0.0.26a0.dist-info/top_level.txt
easyblocks-0.0.0.26a0.dist-info/RECORD
