Metadata-Version: 2.1
Name: easyblocks
Version: 0.0.0.26a0
Summary: Store data in blockchain format easily with Python
Home-page: https://github.com/brunneis/easyblocks
Author: Rodrigo Martínez
Author-email: dev@brunneis.com
License: GNU General Public License v3.0
Platform: UNKNOWN
Classifier: Development Status :: 4 - Beta
Classifier: Environment :: Console
Classifier: Intended Audience :: Developers
Classifier: License :: OSI Approved :: GNU General Public License v3 (GPLv3)
Classifier: Operating System :: POSIX :: Linux
Classifier: Programming Language :: Python :: 3.6
Classifier: Programming Language :: Python :: Implementation :: PyPy
Classifier: Topic :: Software Development :: Libraries :: Python Modules
